security_scanner/__init__.py
security_scanner/src/__init__.py
security_scanner/src/security_scanner.py
security_scanner-0.1.4.dist-info/LICENSE
security_scanner-0.1.4.dist-info/METADATA
security_scanner-0.1.4.dist-info/WHEEL
security_scanner-0.1.4.dist-info/top_level.txt
security_scanner-0.1.4.dist-info/RECORD
