Metadata-Version: 2.1
Name: security-scanner
Version: 0.1.4
Summary: Password/passphrase strength and health checker
Home-page: https://github.com/TheNewThinkTank/security-scanner
Author: TheNewThinkTank
Author-email: gcr84@hotmail.com
License: MIT
Classifier: License :: OSI Approved :: MIT License
Classifier: Programming Language :: Python :: 3.11
Classifier: Operating System :: OS Independent
Requires-Python: >=3.11
License-File: LICENSE
Requires-Dist: bson (>=0.5.10)
Provides-Extra: dev
Requires-Dist: pytest (>=7.0) ; extra == 'dev'
Requires-Dist: twine (>=4.0.2) ; extra == 'dev'
